compare_xml/CHANGELOG.md
compare_xml/CONTRIBUTORS.md
compare_xml/Comparator.py
compare_xml/LICENSE
compare_xml/README.md
compare_xml/__init__.py
tests/__init__.py
tests/test_comperator.py
compare_xml-1.1.0.dist-info/LICENSE
compare_xml-1.1.0.dist-info/METADATA
compare_xml-1.1.0.dist-info/WHEEL
compare_xml-1.1.0.dist-info/top_level.txt
compare_xml-1.1.0.dist-info/RECORD
