Metadata-Version: 2.1
Name: compare-xml
Version: 1.1.0
Summary: Comparator for XML Elements
Home-page: https://projects.f-froehlich.de/compare-xml
Author: Fabian Fröhlich
Author-email: compare-xml@f-froehlich.de
Maintainer: Fabian Fröhlich
Maintainer-email: compare-xml@f-froehlich.de
License: AGPLv3
Download-URL: https://github.com/f-froehlich/compare-xml
Keywords: xml,compare
Platform: UNKNOWN
